huex/__init__.py
huex/conbee.py
huex/light_controller.py
huex/main.py
huex-0.1.0.dist-info/LICENSE
huex-0.1.0.dist-info/METADATA
huex-0.1.0.dist-info/WHEEL
huex-0.1.0.dist-info/entry_points.txt
huex-0.1.0.dist-info/top_level.txt
huex-0.1.0.dist-info/RECORD
